{
  "file": "./models/reports.json",
  "reports": [
    {
      "code": 300,
      "temperature": 3,
      "windSpeed": 4,
      "windDirection": 0,
      "pressure": 1000,
      "timestamp": "2024-07-15T14:36:37.012Z",
      "_id": "9cdecae5-d5e8-4bc4-a965-accf3ad01a0f",
      "stationid": "36d55e7b-4fe9-441a-bc69-2fb9e5e56822"
    },
    {
      "code": 200,
      "temperature": 2,
      "windSpeed": 7,
      "windDirection": "ne",
      "pressure": 1000,
      "timestamp": "2024-07-16T17:56:46.664Z",
      "_id": "321806d5-9324-4f9a-ad18-b44ecf5b2cca",
      "stationid": "189e3866-da41-473c-93d7-1f55b7ea0795"
    },
    {
      "code": 200,
      "temperature": 23,
      "windSpeed": 3,
      "windDirection": "N",
      "pressure": 980,
      "timestamp": "2024-07-17T10:29:23.431Z",
      "_id": "49598098-756d-458d-bfa6-7d31692dc48e",
      "stationid": "3a67cb86-0fbc-41a4-a5fb-4dd0cbffecf5"
    }
  ]
}